{"_ts":[1488338502,1488859717,1488946460],"_r":{"breakdown":{"html":{"bytes":[39403,35283,33407],"requests":[24,15,15]},"js":{"bytes":[530939,533571,533683],"requests":[40,39,39]},"css":{"bytes":[38566,38666,38568],"requests":[5,5,5]},"image":{"bytes":[1748272,2446218,1748722],"requests":[73,72,72]},"flash":{"bytes":[0,0,0],"requests":[0,0,0]},"font":{"bytes":[234204,234153,234222],"requests":[3,3,3]},"other":{"bytes":[2677,2139,2135],"requests":[7,5,5]}},"date":[1488338502,1488859717,1488946460],"domElements":[796,797,796],"domInteractive":[2188,3241,2717],"firstPaint":[1855,2819,2321],"fullyLoaded":[12444,8963,9171],"id":["170301_1M_62K","170307_A9_859","170308_AE_8Q0"],"loadTime":[6702,8395,8431],"render":[2796,4094,3373],"SpeedIndex":[5331,7032,6144],"TTFB":[299,872,284],"videoFrames":[[{"_t":0,"_vc":0},{"_t":2800,"_vc":1},{"_t":3000,"_vc":6},{"_t":4900,"_vc":53},{"_t":6100,"_vc":100}],[{"_t":0,"_vc":0},{"_t":4100,"_vc":6},{"_t":6300,"_vc":37},{"_t":7200,"_vc":67},{"_t":8100,"_vc":100}],[{"_t":0,"_vc":0},{"_t":3400,"_vc":1},{"_t":3700,"_vc":6},{"_t":5800,"_vc":57},{"_t":6900,"_vc":100}]],"visualComplete":[6111,8100,6900]}}