{"_ts":[1551445141,1551532609],"_r":{"breakdown":{"html":{"bytes":[8368,8377],"requests":[5,5]},"js":{"bytes":[365009,365045],"requests":[15,15]},"css":{"bytes":[11673,11673],"requests":[3,3]},"image":{"bytes":[73108,73108],"requests":[5,5]},"flash":{"bytes":[0,0],"requests":[0,0]},"font":{"bytes":[66036,66036],"requests":[2,2]},"video":{"bytes":[0,0],"requests":[0,0]},"other":{"bytes":[413,413],"requests":[7,7]}},"date":[1551445141,1551532609],"domElements":[313,313],"domInteractive":[2483,2550],"firstPaint":[2375.8849999999,2338.7450000009],"fullyLoaded":[3804,3774],"id":["190301_8K_9e722b59cc5d43844843979d92603e7a","190302_5B_38fd018a9e28996563cc7951ea3267e7"],"loadTime":[3294,3262],"render":[2400,2400],"SpeedIndex":[2400,2459],"TTFB":[1161,1242],"videoFrames":[[{"_i":"ms_000000.jpg","_t":0,"_vc":0},{"_i":"ms_002400.jpg","_t":2400,"_vc":100}],[{"_i":"ms_000000.jpg","_t":0,"_vc":0},{"_i":"ms_002400.jpg","_t":2400,"_vc":41},{"_i":"ms_002500.jpg","_t":2500,"_vc":100}]],"visualComplete":[2400,2500],"lighthouse":[62,62],"pagespeed":[79,79]}}