{"_ts":[1512096997,1512184013],"_r":{"breakdown":{"html":{"bytes":[28342,33152],"requests":[9,8]},"js":{"bytes":[280298,338995],"requests":[32,33]},"css":{"bytes":[109098,119163],"requests":[7,9]},"image":{"bytes":[524837,525317],"requests":[31,32]},"flash":{"bytes":[0,0],"requests":[0,0]},"font":{"bytes":[171858,171857],"requests":[5,5]},"video":{"bytes":[0,0],"requests":[0,0]},"other":{"bytes":[305,305],"requests":[1,1]}},"date":[1512096997,1512184013],"domElements":[1426,1430],"domInteractive":[3504,3795],"firstPaint":[2566,2686],"fullyLoaded":[5090,6757],"id":["171201_09_50929f95108941b75bbf58b0af18317e","171202_XT_a77f07bd4dd24da1213e9e1048c0c59c"],"loadTime":[4336,5034],"render":[2676,2767],"SpeedIndex":[3401,3522],"TTFB":[1163,907],"videoFrames":[[{"_i":"frame_0000.jpg","_t":0,"_vc":0},{"_i":"frame_0027.jpg","_t":2700,"_vc":6},{"_i":"frame_0031.jpg","_t":3100,"_vc":12},{"_i":"frame_0034.jpg","_t":3400,"_vc":89},{"_i":"frame_0035.jpg","_t":3500,"_vc":90},{"_i":"frame_0040.jpg","_t":4000,"_vc":100}],[{"_i":"frame_0000.jpg","_t":0,"_vc":0},{"_i":"frame_0028.jpg","_t":2800,"_vc":6},{"_i":"frame_0030.jpg","_t":3000,"_vc":11},{"_i":"frame_0032.jpg","_t":3200,"_vc":11},{"_i":"frame_0034.jpg","_t":3400,"_vc":12},{"_i":"frame_0035.jpg","_t":3500,"_vc":90},{"_i":"frame_0044.jpg","_t":4400,"_vc":100}]],"visualComplete":[4000,4400],"lighthouse":[null,null],"pagespeed":[78,77]}}